sysaid/__init__.py
sysaid/action_items.py
sysaid/add_ons.py
sysaid/assets.py
sysaid/cis.py
sysaid/core.py
sysaid/filters.py
sysaid/lists.py
sysaid/login.py
sysaid/non_resource_scenarios.py
sysaid/password_services.py
sysaid/resource_bundle.py
sysaid/service_requests.py
sysaid/users.py
ezapi_sysaid-0.2.1.dist-info/LICENSE
ezapi_sysaid-0.2.1.dist-info/METADATA
ezapi_sysaid-0.2.1.dist-info/WHEEL
ezapi_sysaid-0.2.1.dist-info/top_level.txt
ezapi_sysaid-0.2.1.dist-info/RECORD
