Metadata-Version: 2.1
Name: ezapi-sysaid
Version: 0.2.1
Summary: A Python wrapper for SysAid REST API
Author-email: Zeheng Li <imzehengl@gmail.com>
Maintainer-email: Zeheng Li <imzehengl@gmail.com>
Project-URL: repository, https://github.com/zehengl/ezapi-sysaid
Project-URL: homepage, https://zehengl.github.io/ezapi-sysaid/
Classifier: Programming Language :: Python :: 3
Classifier: License :: OSI Approved :: MIT License
Classifier: Operating System :: OS Independent
Requires-Python: >=3.8
License-File: LICENSE
Requires-Dist: requests
Requires-Dist: wrapt ==1.16.0
